milan_petstore_sdk/__init__.py
milan_petstore_sdk/sdk.py
milan_petstore_sdk/hooks/__init__.py
milan_petstore_sdk/hooks/hook.py
milan_petstore_sdk/models/__init__.py
milan_petstore_sdk/models/base.py
milan_petstore_sdk/models/pet.py
milan_petstore_sdk/models/utils/cast_models.py
milan_petstore_sdk/models/utils/json_map.py
milan_petstore_sdk/net/__init__.py
milan_petstore_sdk/net/environment/__init__.py
milan_petstore_sdk/net/environment/environment.py
milan_petstore_sdk/net/headers/__init__.py
milan_petstore_sdk/net/headers/base_header.py
milan_petstore_sdk/net/request_chain/__init__.py
milan_petstore_sdk/net/request_chain/request_chain.py
milan_petstore_sdk/net/request_chain/handlers/__init__.py
milan_petstore_sdk/net/request_chain/handlers/base_handler.py
milan_petstore_sdk/net/request_chain/handlers/hook_handler.py
milan_petstore_sdk/net/request_chain/handlers/http_handler.py
milan_petstore_sdk/net/request_chain/handlers/retry_handler.py
milan_petstore_sdk/net/transport/__init__.py
milan_petstore_sdk/net/transport/request.py
milan_petstore_sdk/net/transport/request_error.py
milan_petstore_sdk/net/transport/response.py
milan_petstore_sdk/net/transport/serializer.py
milan_petstore_sdk/net/transport/utils.py
milan_petstore_sdk/services/__init__.py
milan_petstore_sdk/services/pets.py
milan_petstore_sdk/services/utils/base_service.py
milan_petstore_sdk/services/utils/default_headers.py
milan_petstore_sdk/services/utils/validator.py
milan_petstore_sdk-1.0.0.dist-info/METADATA
milan_petstore_sdk-1.0.0.dist-info/WHEEL
milan_petstore_sdk-1.0.0.dist-info/top_level.txt
milan_petstore_sdk-1.0.0.dist-info/RECORD
