Metadata-Version: 2.1
Name: milan-petstore-sdk
Version: 1.0.0
Requires-Python: >=3.7
Requires-Dist: requests >=2.31.0
